setup.py
images_service_client_pearch_digital/__init__.py
images_service_client_pearch_digital/abstractions.py
images_service_client_pearch_digital/client.py
images_service_client_pearch_digital/generators.py
images_service_client_pearch_digital/models.py
pearchimageserviceclient.egg-info/PKG-INFO
pearchimageserviceclient.egg-info/SOURCES.txt
pearchimageserviceclient.egg-info/dependency_links.txt
pearchimageserviceclient.egg-info/top_level.txt