Metadata-Version: 2.1
Name: pearchimageserviceclient
Version: 0.2
Summary: Small Fixes.
Home-page: UNKNOWN
Author: Alejandro
Author-email: alejandrog@pearchdigital.com
License: UNKNOWN
Platform: UNKNOWN
Classifier: Programming Language :: Python :: 3.8
Classifier: License :: OSI Approved :: MIT License
Classifier: Operating System :: OS Independent
Requires-Python: >=3.7
